docs/conf.py
lwe/__init__.py
lwe/debug.py
lwe/main.py
lwe/version.py
lwe/backends/__init__.py
lwe/backends/api/__init__.py
lwe/backends/api/backend.py
lwe/backends/api/conversation.py
lwe/backends/api/conversation_storage_manager.py
lwe/backends/api/database.py
lwe/backends/api/message.py
lwe/backends/api/orm.py
lwe/backends/api/repl.py
lwe/backends/api/request.py
lwe/backends/api/user.py
lwe/backends/api/schema/__init__.py
lwe/backends/api/schema/alembic.ini
lwe/backends/api/schema/updater.py
lwe/backends/api/schema/alembic/env.py
lwe/backends/api/schema/alembic/script.py.mako
lwe/backends/api/schema/alembic/versions/28ec77033b2e_conversation_add_provider_preset.py
lwe/backends/api/schema/alembic/versions/4e642f725923_tools_migration.py
lwe/backends/api/schema/alembic/versions/82656e325f36_migrate_model_data_to_messages_remove_.py
lwe/backends/api/schema/alembic/versions/9a533073a041_user_replace_default_model_with_default_.py
lwe/backends/api/schema/alembic/versions/c7d7803302a9_add_message_metadata_to_message_table.py
lwe/backends/api/schema/alembic/versions/cc8f2aecf9ff_remove_streaming_attribute_from_presets.py
lwe/backends/api/schema/alembic/versions/e7373d57cace_upgrade_openai_presets_to_responses_api.py
lwe/backends/api/schema/alembic/versions/ea7ed165a4ef_preset_config_schema_v2.py
lwe/backends/api/workflow/__init__.py
lwe/backends/api/workflow/ansible.cfg
lwe/backends/api/workflow/inventory.yaml
lwe/backends/api/workflow/action_plugins/__init__.py
lwe/backends/api/workflow/action_plugins/lwe_input.py
lwe/backends/api/workflow/library/__init__.py
lwe/backends/api/workflow/library/lwe_command.py
lwe/backends/api/workflow/library/lwe_llm.py
lwe/backends/api/workflow/library/lwe_sqlite_query.py
lwe/backends/api/workflow/library/text_extractor.py
lwe/core/__init__.py
lwe/core/async_compat.py
lwe/core/cache_manager.py
lwe/core/config.py
lwe/core/constants.py
lwe/core/doc_parser.py
lwe/core/editor.py
lwe/core/error.py
lwe/core/logger.py
lwe/core/monkey_patch.py
llm_workflow_engine-0.22.20.dist-info/METADATA
llm_workflow_engine-0.22.20.dist-info/WHEEL
llm_workflow_engine-0.22.20.dist-info/entry_points.txt
llm_workflow_engine-0.22.20.dist-info/top_level.txt
llm_workflow_engine-0.22.20.dist-info/RECORD
