Metadata-Version: 2.4
Name: llm-workflow-engine
Version: 0.22.20
Summary: CLI tool and workflow manager for common LLMs
Author: Chad Phillips
Author-email: Mahmoud Mabrouk <mahmoudmabrouk.mail@gmail.com>
License-Expression: MIT
Project-URL: Homepage, https://github.com/llm-workflow-engine/llm-workflow-engine
Project-URL: Repository, https://github.com/llm-workflow-engine/llm-workflow-engine
Classifier: Programming Language :: Python :: 3
Classifier: Operating System :: OS Independent
Requires-Python: >=3.10
Requires-Dist: ansible>=8.0
Requires-Dist: ansible-core>=2.15
Requires-Dist: alembic
Requires-Dist: beautifulsoup4
Requires-Dist: docutils>=0.20.1
Requires-Dist: email-validator
Requires-Dist: Jinja2
Requires-Dist: kreuzberg
Requires-Dist: langchain<2,>=1.0.8
Requires-Dist: langchain-core<2,>=1.0.6
Requires-Dist: langchain-community<0.5,>=0.4.1
Requires-Dist: langchain_openai>=0.3.29
Requires-Dist: names
Requires-Dist: numexpr>=2.8.4
Requires-Dist: openpyxl
Requires-Dist: pdfminer.six
Requires-Dist: prompt-toolkit
Requires-Dist: pymupdf4llm
Requires-Dist: pyperclip
Requires-Dist: python-frontmatter
Requires-Dist: PyYAML
Requires-Dist: rich
Requires-Dist: setuptools
Requires-Dist: sqlalchemy>=1.4.48
Requires-Dist: tiktoken
Provides-Extra: dev
Requires-Dist: pytest; extra == "dev"
Requires-Dist: pytest-datadir; extra == "dev"
Requires-Dist: pip-tools; extra == "dev"
Requires-Dist: flake8; extra == "dev"
Requires-Dist: black; extra == "dev"
